AnquanBeiwangDanFanyiXiangmu/README.md
AnquanBeiwangDanFanyiXiangmu/__init__.py
AnquanBeiwangDanFanyiXiangmu/__main__.py
AnquanBeiwangDanFanyiXiangmu/file.epub
AnquanBeiwangDanFanyiXiangmu/index.html
AnquanBeiwangDanFanyiXiangmu/css/__init__.py
AnquanBeiwangDanFanyiXiangmu/css/annotations.css
AnquanBeiwangDanFanyiXiangmu/css/main.css
AnquanBeiwangDanFanyiXiangmu/css/normalize.css
AnquanBeiwangDanFanyiXiangmu/css/popup.css
AnquanBeiwangDanFanyiXiangmu/font/__init__.py
AnquanBeiwangDanFanyiXiangmu/font/fontello.eot
AnquanBeiwangDanFanyiXiangmu/font/fontello.svg
AnquanBeiwangDanFanyiXiangmu/font/fontello.ttf
AnquanBeiwangDanFanyiXiangmu/font/fontello.woff
AnquanBeiwangDanFanyiXiangmu/img/__init__.py
AnquanBeiwangDanFanyiXiangmu/img/annotator-glyph-sprite.png
AnquanBeiwangDanFanyiXiangmu/img/annotator-icon-sprite.png
AnquanBeiwangDanFanyiXiangmu/img/apple-touch-icon.png
AnquanBeiwangDanFanyiXiangmu/img/cancelfullscreen.png
AnquanBeiwangDanFanyiXiangmu/img/close.png
AnquanBeiwangDanFanyiXiangmu/img/fullscreen.png
AnquanBeiwangDanFanyiXiangmu/img/loader.gif
AnquanBeiwangDanFanyiXiangmu/img/menu-icon.png
AnquanBeiwangDanFanyiXiangmu/img/save.png
AnquanBeiwangDanFanyiXiangmu/img/saved.png
AnquanBeiwangDanFanyiXiangmu/img/settings-s.png
AnquanBeiwangDanFanyiXiangmu/img/settings.png
AnquanBeiwangDanFanyiXiangmu/img/star.png
AnquanBeiwangDanFanyiXiangmu/js/__init__.py
AnquanBeiwangDanFanyiXiangmu/js/epub.js
AnquanBeiwangDanFanyiXiangmu/js/epub.min.js
AnquanBeiwangDanFanyiXiangmu/js/epub.min.map
AnquanBeiwangDanFanyiXiangmu/js/hooks.min.js
AnquanBeiwangDanFanyiXiangmu/js/hooks.min.map
AnquanBeiwangDanFanyiXiangmu/js/reader.js
AnquanBeiwangDanFanyiXiangmu/js/reader.js.map
AnquanBeiwangDanFanyiXiangmu/js/reader.min.js
AnquanBeiwangDanFanyiXiangmu/js/reader.min.map
AnquanBeiwangDanFanyiXiangmu/js/hooks/__init__.py
AnquanBeiwangDanFanyiXiangmu/js/hooks/extensions/__init__.py
AnquanBeiwangDanFanyiXiangmu/js/hooks/extensions/highlight.js
anquan_beiwang_dan_fanyi_xiangmu-2024.2.29.0.dist-info/METADATA
anquan_beiwang_dan_fanyi_xiangmu-2024.2.29.0.dist-info/WHEEL
anquan_beiwang_dan_fanyi_xiangmu-2024.2.29.0.dist-info/entry_points.txt
anquan_beiwang_dan_fanyi_xiangmu-2024.2.29.0.dist-info/top_level.txt
anquan_beiwang_dan_fanyi_xiangmu-2024.2.29.0.dist-info/RECORD
